README.md
setup.py
ClassAttendanceManager/ClassAttendanceManager.py
ClassAttendanceManager/__init__.py
ClassAttendanceManager.egg-info/PKG-INFO
ClassAttendanceManager.egg-info/SOURCES.txt
ClassAttendanceManager.egg-info/dependency_links.txt
ClassAttendanceManager.egg-info/top_level.txt