Metadata-Version: 2.1
Name: ClassAttendanceManager
Version: 1.1
Summary: A simple python script to manage students attendance in class in terminal.
Home-page: https://github.com/Navid2zp/ClassAttendanceManager
Author: Navid Zarepak
Author-email: navid2zp@gmail.com
License: MIT
Download-URL: https://pypi.org/project/ClassAttendanceManager/
Platform: UNKNOWN
